replan2eplus/__init__.py
replan2eplus/afn/interfaces.py
replan2eplus/afn/presentation.py
replan2eplus/airboundary/interfaces.py
replan2eplus/airboundary/presentation.py
replan2eplus/constructions/__init__.py
replan2eplus/constructions/interfaces.py
replan2eplus/constructions/logic/update.py
replan2eplus/constructions/logic/utils.py
replan2eplus/constructions/presentation.py
replan2eplus/epnames/keys.py
replan2eplus/errors.py
replan2eplus/examples/defaults.py
replan2eplus/examples/existing.py
replan2eplus/examples/mat_and_const.py
replan2eplus/examples/minimal.py
replan2eplus/examples/subsurfaces.py
replan2eplus/ezcase/main.py
replan2eplus/ezcase/read.py
replan2eplus/ezobjects/afn.py
replan2eplus/ezobjects/airboundary.py
replan2eplus/ezobjects/base.py
replan2eplus/ezobjects/constr_and_mat_utils.py
replan2eplus/ezobjects/construction.py
replan2eplus/ezobjects/epbunch_utils.py
replan2eplus/ezobjects/material.py
replan2eplus/ezobjects/name.py
replan2eplus/ezobjects/subsurface.py
replan2eplus/ezobjects/surface.py
replan2eplus/ezobjects/zone.py
replan2eplus/geometry/contact_points.py
replan2eplus/geometry/coords.py
replan2eplus/geometry/directions.py
replan2eplus/geometry/domain.py
replan2eplus/geometry/domain_calcs.py
replan2eplus/geometry/domain_create.py
replan2eplus/geometry/nonant.py
replan2eplus/geometry/plane.py
replan2eplus/geometry/range.py
replan2eplus/idfobjects/afn.py
replan2eplus/idfobjects/idf.py
replan2eplus/idfobjects/subsurface.py
replan2eplus/idfobjects/zone.py
replan2eplus/materials/interfaces.py
replan2eplus/materials/presentation.py
replan2eplus/paths.py
replan2eplus/py.typed
replan2eplus/subsurfaces/interfaces.py
replan2eplus/subsurfaces/logic.py
replan2eplus/subsurfaces/presentation.py
replan2eplus/subsurfaces/utils.py
replan2eplus/visuals/axis_modifications.py
replan2eplus/visuals/base_plot.py
replan2eplus/visuals/organization.py
replan2eplus/visuals/styles/artists.py
replan2eplus/visuals/styles/interfaces.py
replan2eplus-0.1.9.dist-info/WHEEL
replan2eplus-0.1.9.dist-info/METADATA
replan2eplus-0.1.9.dist-info/RECORD
