Metadata-Version: 2.3
Name: replan2eplus
Version: 0.1.9
Summary: Add your description here
Author: Juliet Nwagwu Ume-Ezeoke
Author-email: Juliet Nwagwu Ume-Ezeoke <jnwagwu@stanford.edu>
Requires-Dist: eppy>=0.5.63
Requires-Dist: geomeppy>=0.11.8
Requires-Dist: ladybug-core>=0.44.19
Requires-Dist: pyprojroot>=0.3.0
Requires-Dist: pytest-cov>=6.2.1
Requires-Dist: rich>=14.1.0
Requires-Dist: utils4plans>=0.1.6
Requires-Python: >=3.13
